{"ranking":[{"name":"Afghanistan","value":58178},{"name":"Albania","value":32790},{"name":"Algeria","value":86052},{"name":"Andorra","value":11818},{"name":"Angola","value":61625},{"name":"Argentina","value":187039},{"name":"Armenia","value":89808},{"name":"Australia","value":382430},{"name":"Austria","value":320874},{"name":"Azerbaijan","value":82954},{"name":"Bahrain","value":27691},{"name":"Bangladesh","value":203091},{"name":"Belarus","value":79518},{"name":"Belgium","value":333728},{"name":"Benin","value":48177},{"name":"Bhutan","value":12488},{"name":"Bolivia","value":78645},{"name":"Bosnia and Herz.","value":357},{"name":"Botswana","value":20464},{"name":"Brazil","value":203963},{"name":"Bulgaria","value":183843},{"name":"Burkina Faso","value":9415},{"name":"Burundi","value":22739},{"name":"Cambodia","value":85690},{"name":"Cameroon","value":113817},{"name":"Canada","value":389526},{"name":"Chad","value":6327},{"name":"Chile","value":141370},{"name":"China","value":357126},{"name":"Colombia","value":151833},{"name":"Congo","value":28552},{"name":"Croatia","value":133372},{"name":"Cuba","value":74214},{"name":"Cyprus","value":80728},{"name":"Czechia","value":311063},{"name":"Denmark","value":259327},{"name":"Dominican Rep.","value":37198},{"name":"Ecuador","value":90414},{"name":"Egypt","value":162122},{"name":"El Salvador","value":46241},{"name":"Estonia","value":120445},{"name":"Ethiopia","value":203449},{"name":"Finland","value":254859},{"name":"France","value":543581},{"name":"Georgia","value":142727},{"name":"Germany","value":592373},{"name":"Ghana","value":166244},{"name":"Greece","value":185408},{"name":"Guatemala","value":81985},{"name":"Honduras","value":41188},{"name":"Hong Kong","value":202066},{"name":"Hungary","value":189825},{"name":"Iceland","value":57856},{"name":"India","value":243329},{"name":"Indonesia","value":385880},{"name":"Iran","value":203098},{"name":"Iraq","value":48545},{"name":"Ireland","value":191117},{"name":"Israel","value":217305},{"name":"Italy","value":358350},{"name":"Jamaica","value":66181},{"name":"Japan","value":534937},{"name":"Jordan","value":65685},{"name":"Kazakhstan","value":72484},{"name":"Kenya","value":299183},{"name":"Kuwait","value":31428},{"name":"Laos","value":9358},{"name":"Latvia","value":69820},{"name":"Lithuania","value":82114},{"name":"Luxembourg","value":73326},{"name":"Madagascar","value":116164},{"name":"Malawi","value":34207},{"name":"Malaysia","value":130416},{"name":"Maldives","value":12996},{"name":"Mali","value":10991},{"name":"Malta","value":37354},{"name":"Mauritania","value":10242},{"name":"Mauritius","value":27153},{"name":"Mexico","value":153779},{"name":"Moldova","value":60658},{"name":"Mongolia","value":40960},{"name":"Montenegro","value":49478},{"name":"Morocco","value":153592},{"name":"Mozambique","value":29501},{"name":"Myanmar","value":88546},{"name":"Namibia","value":11307},{"name":"Nepal","value":163170},{"name":"Netherlands","value":438712},{"name":"New Zealand","value":152720},{"name":"Nicaragua","value":103338},{"name":"Nigeria","value":160109},{"name":"Norway","value":266209},{"name":"Oman","value":42759},{"name":"Pakistan","value":168531},{"name":"Palestine","value":79613},{"name":"Panama","value":32214},{"name":"Paraguay","value":62218},{"name":"Peru","value":98961},{"name":"Philippines","value":314322},{"name":"Poland","value":375534},{"name":"Portugal","value":244150},{"name":"Qatar","value":30241},{"name":"Romania","value":191875},{"name":"Russia","value":206038},{"name":"Rwanda","value":184127},{"name":"San Marino","value":3151},{"name":"Saudi Arabia","value":43874},{"name":"Senegal","value":50555},{"name":"Serbia","value":136124},{"name":"Sierra Leone","value":7714},{"name":"Singapore","value":215241},{"name":"Slovakia","value":99886},{"name":"Slovenia","value":104764},{"name":"South Africa","value":127231},{"name":"South Korea","value":262727},{"name":"Spain","value":374302},{"name":"Sri Lanka","value":196454},{"name":"Sudan","value":24364},{"name":"Sweden","value":314297},{"name":"Switzerland","value":401923},{"name":"Syria","value":54255},{"name":"Taiwan","value":323612},{"name":"Tanzania","value":93019},{"name":"Thailand","value":215381},{"name":"Tunisia","value":116275},{"name":"Turkey","value":169510},{"name":"Uganda","value":134736},{"name":"Ukraine","value":200952},{"name":"United Arab Emirates","value":373},{"name":"United Kingdom","value":427393},{"name":"United States of America","value":409760},{"name":"Uruguay","value":75799},{"name":"Uzbekistan","value":120351},{"name":"Venezuela","value":115308},{"name":"Vietnam","value":222779},{"name":"Yemen","value":52671},{"name":"Zambia","value":37624},{"name":"Zambia","value":66621}]}
